pagebits/main.py
pagebits-0.1.0.dist-info/WHEEL
pagebits-0.1.0.dist-info/METADATA
pagebits-0.1.0.dist-info/RECORD
