Metadata-Version: 2.1
Name: pagebits
Version: 0.1.0
Summary: Static fact storage and site generator
License: MIT
Author: vduseev
Author-email: vagiz@duseev.com
Requires-Python: >=3.9,<4.0
Classifier: License :: OSI Approved :: MIT License
Classifier: Programming Language :: Python :: 3
Classifier: Programming Language :: Python :: 3.9
Requires-Dist: cleo (>=0.8.1,<0.9.0)
